{"player":{"id":"50f347b2-3bdf-4e24-9804-2cd90d323fc4","name":"測試玩家","level":1,"experience":0,"status":0,"lastLogoutTime":1754674888547,"lastLoginTime":1754674882779,"foundingTime":1754640040861,"lastUpdatedTime":1754674888547},"resources":{"nowAmount":{"GOLD":10000,"WOOD":10104,"DIAMOND":10000,"IRON":10104,"STONE":10104,"FOOD":10104},"maxAmount":{"GOLD":999999999,"WOOD":5000000,"DIAMOND":999999999,"IRON":3000000,"STONE":4000000,"FOOD":5000000},"productionRates":{"GOLD":1,"WOOD":60,"DIAMOND":0,"IRON":60,"STONE":60,"FOOD":60},"lastUpdatedTime":1754647247539},"buildings":{"mainHall":{"ownerId":"50f347b2-3bdf-4e24-9804-2cd90d323fc4","buildingId":"mainHall","instanceId":"mainHall_50f347b2-3bdf-4e24-9804-2cd90d323fc4","level":1,"status":"IDLE","buildStartTime":1754640040861,"buildEndTime":0,"positionX":0,"positionY":0}},"inventory":[],"events":[],"terrains":[],"units":[],"trades":[],"version":"1.0","battles":[],"technologies":[],"allianceId":null,"tasks":[]}